j2o/__init__.py
j2o/__main__.py
j2o-0.0.7.dist-info/METADATA
j2o-0.0.7.dist-info/WHEEL
j2o-0.0.7.dist-info/entry_points.txt
j2o-0.0.7.dist-info/licenses/LICENSE
j2o-0.0.7.dist-info/RECORD
